perfectextractor/__init__.py
perfectextractor/extract.py
perfectextractor/apps/__init__.py
perfectextractor/apps/counter/__init__.py
perfectextractor/apps/counter/base.py
perfectextractor/apps/extractor/__init__.py
perfectextractor/apps/extractor/base.py
perfectextractor/apps/extractor/models.py
perfectextractor/apps/extractor/perfectextractor.py
perfectextractor/apps/extractor/posextractor.py
perfectextractor/apps/extractor/recentpastextractor.py
perfectextractor/apps/extractor/utils.py
perfectextractor/apps/extractor/wiktionary.py
perfectextractor/apps/extractor/xml_utils.py
perfectextractor/apps/extractor/config/de_aux_be.txt
perfectextractor/apps/extractor/config/fr_aux_be.txt
perfectextractor/apps/extractor/config/nl_aux_be.txt
perfectextractor/corpora/__init__.py
perfectextractor/corpora/bnc/__init__.py
perfectextractor/corpora/bnc/base.cfg
perfectextractor/corpora/bnc/base.py
perfectextractor/corpora/bnc/counter.py
perfectextractor/corpora/bnc/extractor.py
perfectextractor/corpora/bnc/perfect.cfg
perfectextractor/corpora/bnc/perfect.py
perfectextractor/corpora/bnc/pos.py
perfectextractor/corpora/dpc/__init__.py
perfectextractor/corpora/dpc/base.cfg
perfectextractor/corpora/dpc/base.py
perfectextractor/corpora/dpc/extractor.py
perfectextractor/corpora/dpc/perfect.cfg
perfectextractor/corpora/dpc/perfect.py
perfectextractor/corpora/dpc/pos.py
perfectextractor/corpora/dpc/utils.py
perfectextractor/corpora/opus/__init__.py
perfectextractor/corpora/opus/article.py
perfectextractor/corpora/opus/base.cfg
perfectextractor/corpora/opus/base.py
perfectextractor/corpora/opus/counter.py
perfectextractor/corpora/opus/extractor.py
perfectextractor/corpora/opus/perfect.cfg
perfectextractor/corpora/opus/perfect.py
perfectextractor/corpora/opus/pos.py
perfectextractor/corpora/opus/recentpast.cfg
perfectextractor/corpora/opus/recentpast.py
perfectextractor/corpora/opus/since.cfg
perfectextractor/corpora/opus/since.py
perfectextractor/tests/__init__.py
perfectextractor-0.4.dist-info/LICENSE
perfectextractor-0.4.dist-info/METADATA
perfectextractor-0.4.dist-info/WHEEL
perfectextractor-0.4.dist-info/top_level.txt
perfectextractor-0.4.dist-info/RECORD
