Metadata-Version: 2.1
Name: perfectextractor
Version: 0.4
Summary: Extracting Perfects (and related forms) from parallel corpora
Home-page: https://github.com/UUDigitalHumanitieslab/perfectextractor
Author: Martijn van der Klis
Author-email: M.H.vanderKlis@uu.nl
License: MIT
Platform: UNKNOWN
Classifier: Development Status :: 4 - Beta
Classifier: License :: OSI Approved :: MIT License
Classifier: Programming Language :: Python :: 3
Classifier: Operating System :: OS Independent
Classifier: Topic :: Text Processing :: Linguistic
Requires-Python: >=3.6
Requires-Dist: click
Requires-Dist: lxml
Requires-Dist: requests
